fluency/__init__.py
fluency-0.1.0.dist-info/LICENSE
fluency-0.1.0.dist-info/WHEEL
fluency-0.1.0.dist-info/METADATA
fluency-0.1.0.dist-info/RECORD
